ez_setup.py
setup.py
atd/__init__.py
atd/atd.py
atd.egg-info/PKG-INFO
atd.egg-info/SOURCES.txt
atd.egg-info/dependency_links.txt
atd.egg-info/requires.txt
atd.egg-info/top_level.txt
bin/atddir.py