Metadata-Version: 1.0
Name: atd
Version: 0.1.4
Summary: McAfee ATD API
Home-page: https://pythonhosted.org/atd/
Author: Carlos Munoz
Author-email: charly.munoz@gmail.com
License: UNKNOWN
Platform: UNKNOWN
